setup.py
django_smart_forms.egg-info/PKG-INFO
django_smart_forms.egg-info/SOURCES.txt
django_smart_forms.egg-info/dependency_links.txt
django_smart_forms.egg-info/not-zip-safe
django_smart_forms.egg-info/requires.txt
django_smart_forms.egg-info/top_level.txt
smartforms/__init__.py
smartforms/base.py
smartforms/composite.py
smartforms/formset.py
smartforms/models.py
smartforms/stateful.py
tests/__init__.py
tests/forms.py
tests/models.py
tests/composite/__init__.py
tests/composite/test_attribute_access.py
tests/composite/test_initialization.py
tests/composite/test_iteration.py
tests/composite/test_validation.py
tests/formset/__init__.py
tests/formset/forms.py
tests/formset/test_formset.py
tests/stateful/__init__.py
tests/stateful/forms.py
tests/stateful/test_stateful_form.py