Metadata-Version: 1.1
Name: django-smart-forms
Version: 0.24
Summary: Django smart forms
Home-page: http://lovasb.com
Author: Lovas Bence
Author-email: me@lovasb.com
License: MIT
Keywords: django,forms,smart-forms
Platform: UNKNOWN
Classifier: Programming Language :: Python
Classifier: Topic :: Software Development :: Libraries :: Python Modules
Classifier: Framework :: Django
Classifier: Environment :: Web Environment
Classifier: Operating System :: OS Independent
Classifier: Natural Language :: English
